ftts_client/__init__.py
ftts_client-0.3.2.dist-info/METADATA
ftts_client-0.3.2.dist-info/WHEEL
ftts_client-0.3.2.dist-info/RECORD
