Metadata-Version: 2.4
Name: ftts-client
Version: 0.3.2
Summary: fast tts client
Author-email: wangmengdi <790990241@qq.com>
Requires-Python: >=3.10
Requires-Dist: lameenc
Requires-Dist: numpy
Requires-Dist: result
